Compiled from "ParallelSqrt.java"
public class fr.insalyon.telecom.joofluxtest.parallelization.ParallelSqrt {
  public fr.insalyon.telecom.joofluxtest.parallelization.ParallelSqrt();
    Code:
       0: aload_0       
       1: invokespecial #1                  // Method java/lang/Object."<init>":()V
       4: return        

  public static java.util.List<java.lang.Double> parallel_sqrt(int) throws java.lang.Throwable;
    Code:
       0: iconst_2      
       1: invokestatic  #2                  // Method java/util/concurrent/Executors.newFixedThreadPool:(I)Ljava/util/concurrent/ExecutorService;
       4: astore_1      
       5: new           #3                  // class java/util/ArrayList
       8: dup           
       9: invokespecial #4                  // Method java/util/ArrayList."<init>":()V
      12: astore_2      
      13: new           #3                  // class java/util/ArrayList
      16: dup           
      17: invokespecial #4                  // Method java/util/ArrayList."<init>":()V
      20: astore_3      
      21: iconst_0      
      22: istore        4
      24: iload         4
      26: iload_0       
      27: if_icmpge     62
      30: iload         4
      32: istore        5
      34: aload_2       
      35: aload_1       
      36: new           #5                  // class fr/insalyon/telecom/joofluxtest/parallelization/ParallelSqrt$1
      39: dup           
      40: iload         5
      42: invokespecial #6                  // Method fr/insalyon/telecom/joofluxtest/parallelization/ParallelSqrt$1."<init>":(I)V
      45: invokeinterface #7,  2            // InterfaceMethod java/util/concurrent/ExecutorService.submit:(Ljava/util/concurrent/Callable;)Ljava/util/concurrent/Future;
      50: invokeinterface #8,  2            // InterfaceMethod java/util/List.add:(Ljava/lang/Object;)Z
      55: pop           
      56: iinc          4, 1
      59: goto          24
      62: aload_2       
      63: invokeinterface #9,  1            // InterfaceMethod java/util/List.iterator:()Ljava/util/Iterator;
      68: astore        4
      70: aload         4
      72: invokeinterface #10,  1           // InterfaceMethod java/util/Iterator.hasNext:()Z
      77: ifeq          109
      80: aload         4
      82: invokeinterface #11,  1           // InterfaceMethod java/util/Iterator.next:()Ljava/lang/Object;
      87: checkcast     #12                 // class java/util/concurrent/Future
      90: astore        5
      92: aload_3       
      93: aload         5
      95: invokeinterface #13,  1           // InterfaceMethod java/util/concurrent/Future.get:()Ljava/lang/Object;
     100: invokeinterface #8,  2            // InterfaceMethod java/util/List.add:(Ljava/lang/Object;)Z
     105: pop           
     106: goto          70
     109: aload_1       
     110: invokeinterface #14,  1           // InterfaceMethod java/util/concurrent/ExecutorService.shutdown:()V
     115: aload_3       
     116: areturn       

  public static void main(java.lang.String...) throws java.lang.Throwable;
    Code:
       0: invokestatic  #15                 // Method java/lang/System.nanoTime:()J
       3: lstore_1      
       4: new           #16                 // class java/lang/Integer
       7: dup           
       8: aload_0       
       9: iconst_0      
      10: aaload        
      11: invokespecial #17                 // Method java/lang/Integer."<init>":(Ljava/lang/String;)V
      14: invokevirtual #18                 // Method java/lang/Integer.intValue:()I
      17: invokestatic  #19                 // Method parallel_sqrt:(I)Ljava/util/List;
      20: pop           
      21: invokestatic  #15                 // Method java/lang/System.nanoTime:()J
      24: lload_1       
      25: lsub          
      26: lstore_1      
      27: getstatic     #20                 // Field java/lang/System.out:Ljava/io/PrintStream;
      30: lload_1       
      31: invokevirtual #21                 // Method java/io/PrintStream.println:(J)V
      34: return        
}
